{
  "_fv": 13,
  "_type": "tool",
  "definition": {
    "renderType": 0,
    "texture": "dragur",
    "customModelName": "Normal",
    "name": "Draguraxe",
    "specialInfo": [],
    "creativeTab": {
      "value": "TOOLS"
    },
    "toolType": "Sword",
    "harvestLevel": 1,
    "efficiency": 4.0,
    "attackSpeed": 0.8,
    "enchantability": 6,
    "damageVsEntity": 9.5,
    "usageCount": 300,
    "blocksAffected": [],
    "hasGlow": false,
    "repairItems": [
      {
        "value": "CUSTOM:Draguraxe"
      }
    ],
    "stayInGridWhenCrafting": false,
    "damageOnCrafting": false
  }
}